<?xml version="1.0" encoding="utf-8"?>
<!DOCTYPE hibernate-mapping PUBLIC "-//Hibernate/Hibernate Mapping DTD 3.0//EN"
"http://www.hibernate.org/dtd/hibernate-mapping-3.0.dtd">
<!-- 
    Mapping file autogenerated by MyEclipse Persistence Tools
-->
<hibernate-mapping>
    <class name="com.shlanbao.tzsc.base.mapping.EqmLubricant" table="EQM_LUBRICAT">
        <id name="id" type="java.lang.String">
            <column name="ID" length="50" />
            <generator class="uuid.hex" />
        </id>
        <many-to-one name="eqp_category" class="com.shlanbao.tzsc.base.mapping.MdEqpCategory" fetch="select">
            <column name="EQP_CATEGORY" length="50" />
        </many-to-one>
        <many-to-one name="eqp_type" class="com.shlanbao.tzsc.base.mapping.MdEqpType" fetch="select">
            <column name="EQP_TYPE" length="50" />
        </many-to-one>
        <many-to-one name="create_usr" class="com.shlanbao.tzsc.base.mapping.SysUser" fetch="select">
            <column name="CREATE_USR" length="50" />
        </many-to-one>
        <property name="name" type="java.lang.String">
            <column name="NAME" length="50" />
        </property>
        <property name="cycle" type="java.lang.Integer">
            <column name="CYCLE" length="50" />
        </property>
        <property name="last_time" type="java.util.Date">
            <column name="LAST_TIME" length="50" />
        </property>
        <property name="next_time" type="java.util.Date">
            <column name="NEXT_TIME" length="50" />
        </property>
        <property name="create_time" type="java.util.Date">
            <column name="CREATE_TIME" length="50" />
        </property>
        <property name="rule_id" type="java.lang.String">
            <column name="RULE_ID" length="50" />
        </property>
        <property name="rule_name" type="java.lang.String">
            <column name="RULE_NAME" length="50" />
        </property>
        <property name="status" type="java.lang.Integer">
            <column name="STATUS" length="50" />
        </property>
    </class>
</hibernate-mapping>
