<?xml version="1.0" encoding="utf-8"?>
<!DOCTYPE hibernate-mapping PUBLIC "-//Hibernate/Hibernate Mapping DTD 3.0//EN"
"http://hibernate.sourceforge.net/hibernate-mapping-3.0.dtd">
<!-- 
    Mapping file autogenerated by MyEclipse Persistence Tools
-->
<hibernate-mapping>
    <class name="com.shlanbao.tzsc.base.mapping.QmMassExcipient" table="QM_MASS_EXCIPIENT"   >
        <id name="qmExcipientId" type="java.lang.String">
            <column name="QM_EXCIPIENT_ID" length="50" />
            <generator class="uuid.hex" />
        </id>
        <many-to-one name="qmMassCheck" class="com.shlanbao.tzsc.base.mapping.QmMassCheck" fetch="select">
            <column name="QM_CHECK_ID" length="50" />
        </many-to-one>
        <property name="addUserId" type="java.lang.String">
            <column name="ADD_USER_ID" length="50" />
        </property>
        <property name="addUserTime" type="java.util.Date">
            <column name="ADD_USER_TIME" length="23" />
        </property>
        <property name="modifyUserId" type="java.lang.String">
            <column name="MODIFY_USER_ID" length="50" />
        </property>
        <property name="modifyTime" type="java.util.Date">
            <column name="MODIFY_TIME" length="23" />
        </property>
        <property name="isDelete" type="java.lang.String">
            <column name="IS_DELETE" length="1" />
        </property>
        <property name="checkItem" type="java.lang.String">
            <column name="CHECK_ITEM" length="100" />
        </property>
        <property name="checkRate" type="java.lang.String">
            <column name="CHECK_RATE" length="100" />
        </property>
        <property name="isError" type="java.lang.String">
            <column name="IS_ERROR" length="20" />
        </property>
        <property name="subStandard" type="java.lang.String">
            <column name="SUB_STANDARD" length="20" />
        </property>
        <property name="orderNumber" type="java.lang.Integer">
            <column name="ORDER_NUMBER" length="20" />
        </property>
        <property name="checkTime" type="java.lang.String">
            <column name="CHECK_TIME" length="20" />
        </property>
    </class>
</hibernate-mapping>
