<?xml version="1.0" encoding="utf-8"?>
<!DOCTYPE hibernate-mapping PUBLIC "-//Hibernate/Hibernate Mapping DTD 3.0//EN"
"http://hibernate.sourceforge.net/hibernate-mapping-3.0.dtd">
<!-- 
    Mapping file autogenerated by MyEclipse Persistence Tools
-->
<hibernate-mapping>
    <class name="com.shlanbao.tzsc.base.mapping.QualityCheckInfoParams" table="QUALITY_INSPECTION_PARAM"  >
        <id name="id" type="java.lang.String">
            <column name="ID" length="50" />
            <generator class="uuid.hex" />
        </id>
        <property name="qId" type="java.lang.String">
            <column name="QID" length="50" />
        </property>
        <property name="paType" type="java.lang.String">
            <column name="PA_TYPE" length="50" />
        </property>
        <property name="paTypeCode" type="java.lang.String">
            <column name="PA_TYPE_CODE" />
        </property>
        <property name="pgDes" type="java.lang.String">
            <column name="PG_DES" length="50" />
        </property>
        <property name="paDes" type="java.lang.String">
            <column name="PA_DES" />
        </property>
        <property name="valueF" type="java.lang.String">
            <column name="VALUE_F" length="50" />
        </property>
        <property name="scDeduct" type="java.lang.Double">
            <column name="SC_DEDUCT"  />
        </property>
        <property name="unit" type="java.lang.String">
            <column name="UNIT"  />
        </property>
        <property name="cMean" type="java.lang.String">
            <column name="C_MEAN" />
        </property>
        <property name="cSd" type="java.lang.String">
            <column name="C_SD" length="50" />
        </property>
        <property name="cMin" type="java.lang.String">
            <column name="C_MIN" length="50" />
        </property>
        <property name="cMax" type="java.lang.String">
            <column name="C_MAX" length="50" />
        </property>
        <property name="cCv" type="java.lang.String">
            <column name="C_CV" length="50" />
        </property>
        <property name="cResult" type="java.lang.String">
            <column name="C_RESULT" length="50" />
        </property>
    </class>
</hibernate-mapping>
